LICENSE
README.md
pyproject.toml
setup.cfg
setup.py
src/msdss_base_dotenv/__init__.py
src/msdss_base_dotenv/cli.py
src/msdss_base_dotenv/core.py
src/msdss_base_dotenv/tools.py
src/msdss_base_dotenv.egg-info/PKG-INFO
src/msdss_base_dotenv.egg-info/SOURCES.txt
src/msdss_base_dotenv.egg-info/dependency_links.txt
src/msdss_base_dotenv.egg-info/entry_points.txt
src/msdss_base_dotenv.egg-info/requires.txt
src/msdss_base_dotenv.egg-info/top_level.txt