Metadata-Version: 2.1
Name: msdss-base-dotenv
Version: 0.2.5
Summary: Environmental file management for the Modular Spatial Decision Support Systems (MSDSS) framework
Home-page: https://github.com/rrwen/msdss-base-dotenv
Author: Richard Wen
Author-email: rrwen.dev@gmail.com
License: UNKNOWN
Project-URL: Bug Tracker, https://github.com/rrwen/msdss-base-dotenv/issues
Platform: UNKNOWN
Classifier: Programming Language :: Python :: 3
Classifier: License :: OSI Approved :: MIT License
Classifier: Operating System :: OS Independent
Requires-Python: >=3.8
License-File: LICENSE
